wdlparse/__init__.py
wdlparse/dev/WdlLexer.py
wdlparse/dev/WdlParser.py
wdlparse/dev/WdlParserListener.py
wdlparse/dev/WdlParserVisitor.py
wdlparse/dev/__init__.py
wdlparse/draft2/__init__.py
wdlparse/draft2/wdl_parser.py
wdlparse/v1/WdlV1Lexer.py
wdlparse/v1/WdlV1Parser.py
wdlparse/v1/WdlV1ParserListener.py
wdlparse/v1/WdlV1ParserVisitor.py
wdlparse/v1/__init__.py
wdlparse-0.1.0.dist-info/LICENSE
wdlparse-0.1.0.dist-info/METADATA
wdlparse-0.1.0.dist-info/WHEEL
wdlparse-0.1.0.dist-info/top_level.txt
wdlparse-0.1.0.dist-info/RECORD
